{
  "version": "7",
  "dialect": "postgresql",
  "entries": [
    {
      "idx": 0,
      "version": "7",
      "when": 1734721824214,
      "tag": "0000_melted_maestro",
      "breakpoints": true
    },
    {
      "idx": 1,
      "version": "7",
      "when": 1734723817400,
      "tag": "0001_orange_scream",
      "breakpoints": true
    },
    {
      "idx": 2,
      "version": "7",
      "when": 1734725445598,
      "tag": "0002_salty_zeigeist",
      "breakpoints": true
    },
    {
      "idx": 3,
      "version": "7",
      "when": 1734817083718,
      "tag": "0003_cuddly_the_hunter",
      "breakpoints": true
    },
    {
      "idx": 4,
      "version": "7",
      "when": 1734817248490,
      "tag": "0004_long_blink",
      "breakpoints": true
    },
    {
      "idx": 5,
      "version": "7",
      "when": 1734817300907,
      "tag": "0005_bitter_scourge",
      "breakpoints": true
    },
    {
      "idx": 6,
      "version": "7",
      "when": 1734817330262,
      "tag": "0006_stale_sister_grimm",
      "breakpoints": true
    },
    {
      "idx": 7,
      "version": "7",
      "when": 1734817764562,
      "tag": "0007_plain_umar",
      "breakpoints": true
    },
    {
      "idx": 8,
      "version": "7",
      "when": 1734818202239,
      "tag": "0008_classy_gorilla_man",
      "breakpoints": true
    },
    {
      "idx": 9,
      "version": "7",
      "when": 1734818247250,
      "tag": "0009_steep_junta",
      "breakpoints": true
    },
    {
      "idx": 10,
      "version": "7",
      "when": 1734818602641,
      "tag": "0010_wide_wrecker",
      "breakpoints": true
    },
    {
      "idx": 11,
      "version": "7",
      "when": 1734819380099,
      "tag": "0011_quick_oracle",
      "breakpoints": true
    },
    {
      "idx": 12,
      "version": "7",
      "when": 1736694500420,
      "tag": "0012_omniscient_betty_ross",
      "breakpoints": true
    },
    {
      "idx": 13,
      "version": "7",
      "when": 1742165125178,
      "tag": "0013_lame_loners",
      "breakpoints": true
    }
  ]
}